spie/__init__.py
spie/core.py
spie-0.1.0.dist-info/LICENSE.txt
spie-0.1.0.dist-info/METADATA
spie-0.1.0.dist-info/WHEEL
spie-0.1.0.dist-info/top_level.txt
spie-0.1.0.dist-info/RECORD
