Metadata-Version: 2.1
Name: spie
Version: 0.1.0
Summary: Sample-based methods for simultaneous prediction interval estimation.
Home-page: https://github.com/ssokota/spie
Author: Samuel Sokota
Author-email: ssokota@gmail.com
License: LICENSE.txt
Platform: UNKNOWN
Requires-Python: >=3.6
Requires-Dist: numpy (>=1.15.0)
Requires-Dist: matplotlib (>=2.0.0)
